RTL/RV64/modules/CLINT.v
module clint #(
    parameter XLEN = 64,
    parameter CLK_FREQ  = 100_000_000,  // CPU 클럭 주파수: 100MHz
    parameter TICK_FREQ = 1_000         // 1초당 tick 횟수: 1000번
                                        // DIVIDER = 100_000_000 / 1_000 = 100_000
)(
    input  wire        clk,
    input  wire        rst,
 
    // 입력
    input  wire        write_enable,
    input  wire [XLEN-1:0] write_data,
    input  wire [XLEN-1:0] write_address,
    input  wire [XLEN-1:0] read_address,

    // 출력
    output reg  [XLEN-1:0] read_data,
    output wire        timer_interrupt
);
 
// ============================================================
// 1. 클럭 분주기 (100MHz → 1kHz tick 생성)
//    100,000,000 / 1,000 = 100,000 클럭마다 tick 1번
// ============================================================
localparam DIVIDER = CLK_FREQ / TICK_FREQ;  // 100_000
 
reg [$clog2(DIVIDER)-1:0] div_cnt;
reg                        tick;
 
always @(posedge clk) begin
    if (rst) begin
        div_cnt <= 0;
        tick    <= 1'b0;
    end else if (div_cnt == DIVIDER - 1) begin
        div_cnt <= 0;
        tick    <= 1'b1;
    end else begin
        div_cnt <= div_cnt + 1;
        tick    <= 1'b0;
    end
end
 
// ============================================================
// 2. MTIME (읽기/쓰기 가능, tick마다 +1)
// ============================================================
reg [63:0] mtime;
 
always @(posedge clk) begin
    if (rst) begin
        mtime <= 64'b0;
    end else if (write_enable) begin
        case (write_address)
            64'h0000_0000_0200_0000: mtime[XLEN-1:0]  <= write_data;  // high 쓰기
            default: ;
        endcase
    end else if (tick) begin
        mtime <= mtime + 1;  // 100,000클럭마다 +1
    end
end
 
// ============================================================
// 3. MTIMECMP (읽기/쓰기 가능, 증가 로직 없음)
// ============================================================
reg [63:0] mtimecmp;
 
always @(posedge clk) begin
    if (rst) begin
        mtimecmp <= 64'hFFFF_FFFF_FFFF_FFFF;  // 초기값: 최댓값
    end else if (write_enable) begin
        case (write_address)
            64'h0000_0000_0200_0008: mtimecmp[XLEN-1:0]  <= write_data;  // low 쓰기
            default: ;
        endcase
    end
end
 
// ============================================================
// 4. 메모리 읽기 (read_address로 해당 데이터 인출)
// ============================================================
always @(*) begin
    case (read_address)
        64'h0000_0000_0200_0000: read_data = mtime[XLEN-1:0];     // MTIME low
        64'h0000_0000_0200_0008: read_data = mtimecmp[XLEN-1:0];  // MTIMECMP lowq
        default: read_data = {XLEN{1'b0}};
    endcase
end
 
// ============================================================
// 5. 타이머 인터럽트
//    assign timer_interrupt = (mtime >= mtimecmp)
// ============================================================
assign timer_interrupt = (mtime >= mtimecmp) ? 1'b1 : 1'b0;
 
endmodule

RTL/testbenches/clint_tb.v
`timescale 1ns / 1ps
 
// ============================================================
// CLINT 테스트벤치
// 테스트 항목:
//   1. 리셋 후 mtime = 0 확인
//   2. mtime tick 증가 확인
//   3. mtime 쓰기 확인
//   4. mtimecmp 쓰기 확인
//   5. timer_interrupt 발생 확인 (mtime >= mtimecmp)
//   6. mtimecmp 갱신 후 timer_interrupt 클리어 확인
// ============================================================
 
module clint_tb;
 
// 시뮬레이션용 파라미터 (빠른 시뮬을 위해 작은 값 사용)
localparam CLK_FREQ  = 10;   // 10Hz
localparam TICK_FREQ = 2;    // 2Hz → 5클럭마다 tick 1번
localparam CLK_PERIOD = 10;  // 10ns
 
// ============================================================
// 신호 선언
// ============================================================
reg         clk;
reg         rst;
reg         write_enable;
reg  [31:0] write_data;
reg  [31:0] write_address;
reg  [31:0] read_address;
wire [31:0] read_data;
wire        timer_interrupt;
 
// ============================================================
// DUT 인스턴스
// ============================================================
clint #(
    .CLK_FREQ (CLK_FREQ),
    .TICK_FREQ(TICK_FREQ)
) dut (
    .clk           (clk),
    .rst           (rst),
    .write_enable  (write_enable),
    .write_data    (write_data),
    .write_address (write_address),
    .read_address  (read_address),
    .read_data     (read_data),
    .timer_interrupt(timer_interrupt)
);
 
// ============================================================
// 클럭 생성
// ============================================================
initial clk = 0;
always #(CLK_PERIOD/2) clk = ~clk;
 
// ============================================================
// 태스크: 쓰기
// ============================================================
task write_reg;
    input [31:0] addr;
    input [31:0] data;
    begin
        @(posedge clk);
        write_address = addr;
        write_data    = data;
        write_enable  = 1;
        @(posedge clk);
        write_enable  = 0;
    end
endtask
 
// ============================================================
// 태스크: 읽기
// ============================================================
task read_reg;
    input [31:0] addr;
    begin
        @(posedge clk);
        read_address = addr;
    end
endtask
 
// ============================================================
// 메인 테스트
// ============================================================
initial begin
    $dumpfile("clint_tb.vcd");
    $dumpvars(0, clint_tb);
 
    // 초기값
    rst           = 1;
    write_enable  = 0;
    write_data    = 0;
    write_address = 0;
    read_address  = 0;
 
    // -------------------------------------------------------
    // 테스트 1: 리셋 후 mtime = 0 확인
    // -------------------------------------------------------
    repeat(3) @(posedge clk);
    rst = 0;
    $display("=== 테스트 1: 리셋 해제 ===");
    read_reg(32'h0200_0000);
    @(posedge clk);
    $display("MTIME low  = %0d (기대값: 0)", read_data);
    read_reg(32'h0200_0004);
    @(posedge clk);
    $display("MTIME high = %0d (기대값: 0)", read_data);
 
    // -------------------------------------------------------
    // 테스트 2: mtime tick 증가 확인
    // 5클럭마다 tick 1번 → 20클럭 후 mtime = 4
    // -------------------------------------------------------
    $display("\n=== 테스트 2: mtime tick 증가 확인 ===");
    repeat(20) @(posedge clk);
    read_reg(32'h0200_0000);
    @(posedge clk);
    $display("MTIME low = %0d (기대값: 4 근처)", read_data);
 
    // -------------------------------------------------------
    // 테스트 3: mtime 쓰기 확인
    // -------------------------------------------------------
    $display("\n=== 테스트 3: mtime 쓰기 확인 ===");
    write_reg(32'h0200_0000, 32'd999);  // mtime low = 999
    write_reg(32'h0200_0004, 32'd0);    // mtime high = 0
    read_reg(32'h0200_0000);
    @(posedge clk);
    $display("MTIME low = %0d (기대값: 999)", read_data);
 
    // -------------------------------------------------------
    // 테스트 4: mtimecmp 쓰기 확인
    // -------------------------------------------------------
    $display("\n=== 테스트 4: mtimecmp 쓰기 확인 ===");
    write_reg(32'h0200_0008, 32'd50);  // mtimecmp low = 50
    write_reg(32'h0200_000C, 32'd0);   // mtimecmp high = 0
    read_reg(32'h0200_0008);
    @(posedge clk);
    $display("MTIMECMP low = %0d (기대값: 50)", read_data);
 
    // -------------------------------------------------------
    // 테스트 5: timer_interrupt 발생 확인
    // mtime을 작은 값으로 리셋 후 mtimecmp = 10 설정
    // mtime이 10 도달하면 interrupt = 1
    // -------------------------------------------------------
    $display("\n=== 테스트 5: timer_interrupt 발생 확인 ===");
    write_reg(32'h0200_0000, 32'd0);   // mtime low 리셋
    write_reg(32'h0200_0004, 32'd0);   // mtime high 리셋
    write_reg(32'h0200_0008, 32'hFFFF_FFFF);  // 1. low를 먼저 최대값으로 막아놓고
    write_reg(32'h0200_000C, 32'd0);           // 2. high 설정
    write_reg(32'h0200_0008, 32'd10);          // 3. low 최종값 설정
 
    repeat(100) @(posedge clk);
    $display("timer_interrupt = %0d (기대값: 1)", timer_interrupt);
    read_reg(32'h0200_0000);
    @(posedge clk);
    $display("현재 MTIME low = %0d", read_data);
 
    // -------------------------------------------------------
    // 테스트 6: mtimecmp 갱신 후 timer_interrupt 클리어
    // -------------------------------------------------------
    $display("\n=== 테스트 6: mtimecmp 갱신 후 interrupt 클리어 ===");
    write_reg(32'h0200_000C, 32'hFFFF_FFFF);  
    write_reg(32'h0200_0008, 32'hFFFF_FFFF); 
    @(posedge clk);
    $display("timer_interrupt = %0d (기대값: 0)", timer_interrupt);
 
    $display("\n=== 테스트 완료 ===");
    #100;
    $finish;
end
 
// ============================================================
// interrupt 변화 모니터링
// ============================================================
always @(posedge timer_interrupt)
    $display("[interrupt 발생] timer_interrupt = 1, 시각 = %0t ns", $time);
 
always @(negedge timer_interrupt)
    $display("[interrupt 클리어] timer_interrupt = 0, 시각 = %0t ns", $time);
 
endmodule

RTL/RV64/testbenches/results/waveforms/clint_tb.vcd
$date
	Sat Mar 28 20:22:25 2026
$end
$version
	Icarus Verilog
$end
$timescale
	1ps
$end
$scope module clint_tb $end
$var wire 1 ! timer_interrupt $end
$var wire 32 " read_data [31:0] $end
$var parameter 32 # CLK_FREQ $end
$var parameter 32 $ CLK_PERIOD $end
$var parameter 32 % TICK_FREQ $end
$var reg 1 & clk $end
$var reg 32 ' read_address [31:0] $end
$var reg 1 ( rst $end
$var reg 32 ) write_address [31:0] $end
$var reg 32 * write_data [31:0] $end
$var reg 1 + write_enable $end
$scope module dut $end
$var wire 1 & clk $end
$var wire 32 , read_address [31:0] $end
$var wire 1 ( rst $end
$var wire 32 - write_address [31:0] $end
$var wire 32 . write_data [31:0] $end
$var wire 1 + write_enable $end
$var wire 1 ! timer_interrupt $end
$var parameter 32 / CLK_FREQ $end
$var parameter 32 0 DIVIDER $end
$var parameter 32 1 TICK_FREQ $end
$var reg 3 2 div_cnt [2:0] $end
$var reg 64 3 mtime [63:0] $end
$var reg 64 4 mtimecmp [63:0] $end
$var reg 32 5 read_data [31:0] $end
$var reg 1 6 tick $end
$upscope $end
$scope task read_reg $end
$var reg 32 7 addr [31:0] $end
$upscope $end
$scope task write_reg $end
$var reg 32 8 addr [31:0] $end
$var reg 32 9 data [31:0] $end
$upscope $end
$upscope $end
$enddefinitions $end
$comment Show the parameter values. $end
$dumpall
b10 1
b101 0
b1010 /
b10 %
b1010 $
b1010 #
$end
#0
$dumpvars
bx 9
bx 8
bx 7
x6
b0 5
bx 4
bx 3
bx 2
b0 .
b0 -
b0 ,
0+
b0 *
b0 )
1(
b0 '
0&
b0 "
x!
$end
#5000
0!
06
b0 2
b0 3
b1111111111111111111111111111111111111111111111111111111111111111 4
1&
#10000
0&
#15000
1&
#20000
0&
#25000
b1 2
b10000000000000000000000000 7
0(
1&
#30000
0&
#35000
b10 2
b10000000000000000000000000 '
b10000000000000000000000000 ,
1&
#40000
0&
#45000
b11 2
b10000000000000000000000100 7
1&
#50000
0&
#55000
b100 2
b10000000000000000000000100 '
b10000000000000000000000100 ,
1&
#60000
0&
#65000
16
b0 2
1&
#70000
0&
#75000
b1 3
06
b1 2
1&
#80000
0&
#85000
b10 2
1&
#90000
0&
#95000
b11 2
1&
#100000
0&
#105000
b100 2
1&
#110000
0&
#115000
16
b0 2
1&
#120000
0&
#125000
06
b1 2
b10 3
1&
#130000
0&
#135000
b10 2
1&
#140000
0&
#145000
b11 2
1&
#150000
0&
#155000
b100 2
1&
#160000
0&
#165000
16
b0 2
1&
#170000
0&
#175000
b11 3
06
b1 2
1&
#180000
0&
#185000
b10 2
1&
#190000
0&
#195000
b11 2
1&
#200000
0&
#205000
b100 2
1&
#210000
0&
#215000
16
b0 2
1&
#220000
0&
#225000
06
b1 2
b100 3
1&
#230000
0&
#235000
b10 2
1&
#240000
0&
#245000
b11 2
1&
#250000
0&
#255000
b100 2
1&
#260000
0&
#265000
16
b0 2
b10000000000000000000000000 7
1&
#270000
0&
#275000
b101 3
06
b1 2
b101 "
b101 5
b10000000000000000000000000 '
b10000000000000000000000000 ,
1&
#280000
0&
#285000
b10 2
b1111100111 9
b10000000000000000000000000 8
1&
#290000
0&
#295000
b1111100111 "
b1111100111 5
b1111100111 3
b11 2
1+
b1111100111 *
b1111100111 .
b10000000000000000000000000 )
b10000000000000000000000000 -
1&
#300000
0&
#305000
b100 2
b0 9
b10000000000000000000000100 8
0+
1&
#310000
0&
#315000
16
b0 2
1+
b0 *
b0 .
b10000000000000000000000100 )
b10000000000000000000000100 -
1&
#320000
0&
#325000
06
b1 2
0+
1&
#330000
0&
#335000
b10 2
1&
#340000
0&
#345000
b11 2
b110010 9
b10000000000000000000001000 8
1&
#350000
0&
#355000
b1111111111111111111111111111111100000000000000000000000000110010 4
b100 2
1+
b110010 *
b110010 .
b10000000000000000000001000 )
b10000000000000000000001000 -
1&
#360000
0&
#365000
16
b0 2
b0 9
b10000000000000000000001100 8
0+
1&
#370000
0&
#375000
1!
b110010 4
06
b1 2
1+
b0 *
b0 .
b10000000000000000000001100 )
b10000000000000000000001100 -
1&
#380000
0&
#385000
b10 2
b10000000000000000000001000 7
0+
1&
#390000
0&
#395000
b11 2
b110010 "
b110010 5
b10000000000000000000001000 '
b10000000000000000000001000 ,
1&
#400000
0&
#405000
b100 2
b10000000000000000000000000 8
1&
#410000
0&
#415000
0!
b0 3
16
b0 2
1+
b10000000000000000000000000 )
b10000000000000000000000000 -
1&
#420000
0&
#425000
06
b1 2
b10000000000000000000000100 8
0+
1&
#430000
0&
#435000
b10 2
1+
b10000000000000000000000100 )
b10000000000000000000000100 -
1&
#440000
0&
#445000
b11 2
b11111111111111111111111111111111 9
b10000000000000000000001000 8
0+
1&
#450000
0&
#455000
b11111111111111111111111111111111 "
b11111111111111111111111111111111 5
b11111111111111111111111111111111 4
b100 2
1+
b11111111111111111111111111111111 *
b11111111111111111111111111111111 .
b10000000000000000000001000 )
b10000000000000000000001000 -
1&
#460000
0&
#465000
16
b0 2
b0 9
b10000000000000000000001100 8
0+
1&
#470000
0&
#475000
06
b1 2
1+
b0 *
b0 .
b10000000000000000000001100 )
b10000000000000000000001100 -
1&
#480000
0&
#485000
b10 2
b1010 9
b10000000000000000000001000 8
0+
1&
#490000
0&
#495000
b1010 "
b1010 5
b1010 4
b11 2
1+
b1010 *
b1010 .
b10000000000000000000001000 )
b10000000000000000000001000 -
1&
#500000
0&
#505000
b100 2
0+
1&
#510000
0&
#515000
16
b0 2
1&
#520000
0&
#525000
06
b1 2
b1 3
1&
#530000
0&
#535000
b10 2
1&
#540000
0&
#545000
b11 2
1&
#550000
0&
#555000
b100 2
1&
#560000
0&
#565000
16
b0 2
1&
#570000
0&
#575000
b10 3
06
b1 2
1&
#580000
0&
#585000
b10 2
1&
#590000
0&
#595000
b11 2
1&
#600000
0&
#605000
b100 2
1&
#610000
0&
#615000
16
b0 2
1&
#620000
0&
#625000
06
b1 2
b11 3
1&
#630000
0&
#635000
b10 2
1&
#640000
0&
#645000
b11 2
1&
#650000
0&
#655000
b100 2
1&
#660000
0&
#665000
16
b0 2
1&
#670000
0&
#675000
b100 3
06
b1 2
1&
#680000
0&
#685000
b10 2
1&
#690000
0&
#695000
b11 2
1&
#700000
0&
#705000
b100 2
1&
#710000
0&
#715000
16
b0 2
1&
#720000
0&
#725000
06
b1 2
b101 3
1&
#730000
0&
#735000
b10 2
1&
#740000
0&
#745000
b11 2
1&
#750000
0&
#755000
b100 2
1&
#760000
0&
#765000
16
b0 2
1&
#770000
0&
#775000
b110 3
06
b1 2
1&
#780000
0&
#785000
b10 2
1&
#790000
0&
#795000
b11 2
1&
#800000
0&
#805000
b100 2
1&
#810000
0&
#815000
16
b0 2
1&
#820000
0&
#825000
06
b1 2
b111 3
1&
#830000
0&
#835000
b10 2
1&
#840000
0&
#845000
b11 2
1&
#850000
0&
#855000
b100 2
1&
#860000
0&
#865000
16
b0 2
1&
#870000
0&
#875000
b1000 3
06
b1 2
1&
#880000
0&
#885000
b10 2
1&
#890000
0&
#895000
b11 2
1&
#900000
0&
#905000
b100 2
1&
#910000
0&
#915000
16
b0 2
1&
#920000
0&
#925000
06
b1 2
b1001 3
1&
#930000
0&
#935000
b10 2
1&
#940000
0&
#945000
b11 2
1&
#950000
0&
#955000
b100 2
1&
#960000
0&
#965000
16
b0 2
1&
#970000
0&
#975000
1!
b1010 3
06
b1 2
1&
#980000
0&
#985000
b10 2
1&
#990000
0&
#995000
b11 2
1&
#1000000
0&
#1005000
b100 2
1&
#1010000
0&
#1015000
16
b0 2
1&
#1020000
0&
#1025000
06
b1 2
b1011 3
1&
#1030000
0&
#1035000
b10 2
1&
#1040000
0&
#1045000
b11 2
1&
#1050000
0&
#1055000
b100 2
1&
#1060000
0&
#1065000
16
b0 2
1&
#1070000
0&
#1075000
b1100 3
06
b1 2
1&
#1080000
0&
#1085000
b10 2
1&
#1090000
0&
#1095000
b11 2
1&
#1100000
0&
#1105000
b100 2
1&
#1110000
0&
#1115000
16
b0 2
1&
#1120000
0&
#1125000
06
b1 2
b1101 3
1&
#1130000
0&
#1135000
b10 2
1&
#1140000
0&
#1145000
b11 2
1&
#1150000
0&
#1155000
b100 2
1&
#1160000
0&
#1165000
16
b0 2
1&
#1170000
0&
#1175000
b1110 3
06
b1 2
1&
#1180000
0&
#1185000
b10 2
1&
#1190000
0&
#1195000
b11 2
1&
#1200000
0&
#1205000
b100 2
1&
#1210000
0&
#1215000
16
b0 2
1&
#1220000
0&
#1225000
06
b1 2
b1111 3
1&
#1230000
0&
#1235000
b10 2
1&
#1240000
0&
#1245000
b11 2
1&
#1250000
0&
#1255000
b100 2
1&
#1260000
0&
#1265000
16
b0 2
1&
#1270000
0&
#1275000
b10000 3
06
b1 2
1&
#1280000
0&
#1285000
b10 2
1&
#1290000
0&
#1295000
b11 2
1&
#1300000
0&
#1305000
b100 2
1&
#1310000
0&
#1315000
16
b0 2
1&
#1320000
0&
#1325000
06
b1 2
b10001 3
1&
#1330000
0&
#1335000
b10 2
1&
#1340000
0&
#1345000
b11 2
1&
#1350000
0&
#1355000
b100 2
1&
#1360000
0&
#1365000
16
b0 2
1&
#1370000
0&
#1375000
b10010 3
06
b1 2
1&
#1380000
0&
#1385000
b10 2
1&
#1390000
0&
#1395000
b11 2
1&
#1400000
0&
#1405000
b100 2
1&
#1410000
0&
#1415000
16
b0 2
1&
#1420000
0&
#1425000
06
b1 2
b10011 3
1&
#1430000
0&
#1435000
b10 2
1&
#1440000
0&
#1445000
b11 2
1&
#1450000
0&
#1455000
b100 2
1&
#1460000
0&
#1465000
16
b0 2
1&
#1470000
0&
#1475000
b10100 3
06
b1 2
1&
#1480000
0&
#1485000
b10 2
1&
#1490000
0&
#1495000
b11 2
1&
#1500000
0&
#1505000
b100 2
b10000000000000000000000000 7
1&
#1510000
0&
#1515000
16
b0 2
b10100 "
b10100 5
b10000000000000000000000000 '
b10000000000000000000000000 ,
1&
#1520000
0&
#1525000
b10101 "
b10101 5
06
b1 2
b10101 3
b11111111111111111111111111111111 9
b10000000000000000000001100 8
1&
#1530000
0&
#1535000
0!
b1111111111111111111111111111111100000000000000000000000000001010 4
b10 2
1+
b11111111111111111111111111111111 *
b11111111111111111111111111111111 .
b10000000000000000000001100 )
b10000000000000000000001100 -
1&
#1540000
0&
#1545000
b11 2
b10000000000000000000001000 8
0+
1&
#1550000
0&
#1555000
b1111111111111111111111111111111111111111111111111111111111111111 4
b100 2
1+
b10000000000000000000001000 )
b10000000000000000000001000 -
1&
#1560000
0&
#1565000
16
b0 2
0+
1&
#1570000
0&
#1575000
b10110 "
b10110 5
b10110 3
06
b1 2
1&
#1580000
0&
#1585000
b10 2
1&
#1590000
0&
#1595000
b11 2
1&
#1600000
0&
#1605000
b100 2
1&
#1610000
0&
#1615000
16
b0 2
1&
#1620000
0&
#1625000
b10111 "
b10111 5
06
b1 2
b10111 3
1&
#1630000
0&
#1635000
b10 2
1&
#1640000
0&
#1645000
b11 2
1&
#1650000
0&
#1655000
b100 2
1&
#1660000
0&
#1665000
16
b0 2
1&
#1670000
0&
#1675000
b11000 "
b11000 5
b11000 3
06
b1 2
1&
