RTL/modules/CSR_File.v
`include "modules/headers/csr_funct3.vh"

module CSRFile #(
    parameter XLEN = 32
)(
    input clk,                            // clock signal
    input clk_enable,
    input reset,                          // reset signal
    input trapped,
    input mret_executed,
    input csr_write_enable,               // write enable signal
    input [11:0] csr_read_address,        // address to read
    input [11:0] csr_write_address,       // address to write
    input [XLEN-1:0] csr_write_data,      // data to write
    input instruction_retired,
    input valid_csr_address,
    input timer_interrupt_pending,

    input pre_trap_handler,
    input [XLEN-1:0] enter_pc,
    input [XLEN-1:0] trap_cause,
    output wire [XLEN-1:0] vector_address,
    output wire [XLEN-1:0] return_address,

    output reg [XLEN-1:0] csr_read_out,   // data from CSR Unit
    output reg csr_ready,              // signal to stall the process while accessing the CSR until it outputs the desired value.
    output mstatus_mie, 
    output mie_mtie

    );

    wire [XLEN-1:0] mvendorid = 32'h52_56_4B_43;    // "RVKC" ; "R"ISC-"V", "K"HWL & "C"hoiCube84.
    wire [XLEN-1:0] marchid   = 32'h34_36_53_35;    // "46S5" ; "46"F arch based "S"uper scalar "5"-Stage Pipeline Architecture.
    wire [XLEN-1:0] mimpid    = 32'h34_36_49_31;    // "46I1" ; "46" instructions RISC-V RV32"I" Revision "1".
    wire [XLEN-1:0] mhartid   = 32'h0;
    wire [XLEN-1:0] misa      = 32'h40001100;    // MXL = 32; misa[31:30] = 01. RV32"I"; misa[8] = 1.
    wire [XLEN-1:0] mip       = {24'b0, timer_interrupt_pending, 7'b0}; // MIP[7] = MTIP (Machine Timer Interrupt Pending)
    
    reg MIE;
    reg MPIE;
    wire [1:0] MPP = 2'b11;
    wire [XLEN-1:0] mstatus = {19'b0, MPP, 3'b0, MPIE, 3'b0, MIE, 3'b0};

    reg [XLEN-1:0] mtvec;
    reg [XLEN-1:0] mepc;
    reg [XLEN-1:0] mcause;
    reg [XLEN-1:0] mscratch;

    reg [XLEN-1:0] mie;
    reg [63:0] mcycle;
    reg [63:0] minstret;

    reg csr_processing;
    reg [XLEN-1:0] csr_read_data;

    wire csr_access;
    assign csr_access = valid_csr_address;

    assign mstatus_mie = MIE;
    assign mie_mtie = mie[7];

    assign vector_address = pre_trap_handler ? mtvec : {XLEN{1'b0}};
    assign return_address = pre_trap_handler ? mepc : {XLEN{1'b0}};

    localparam [XLEN-1:0] DEFAULT_mtvec  = 32'h00006D60;
    localparam [XLEN-1:0] DEFAULT_mepc   = {XLEN{1'b0}};
    localparam [XLEN-1:0] DEFAULT_mcause = {XLEN{1'b0}};
    localparam [XLEN-1:0] DEFAULT_mscratch = {XLEN{1'b0}};
    localparam [XLEN-1:0] DEFAULT_mcycle = 32'b0;
    localparam [XLEN-1:0] DEFAULT_minstret = 32'b0;
    localparam [XLEN-1:0] DEFAULT_mie    = 32'b0;

    // Read Operation.
    always @(*) begin
        case (csr_read_address)
            12'hB00: csr_read_data = mcycle[XLEN-1:0];
            12'hB02: csr_read_data = minstret[XLEN-1:0];
            12'hB80: csr_read_data = mcycle[63:32];
            12'hB82: csr_read_data = minstret[63:32];
            12'hF11: csr_read_data = mvendorid;
            12'hF12: csr_read_data = marchid;
            12'hF13: csr_read_data = mimpid;
            12'hF14: csr_read_data = mhartid;
            12'h300: csr_read_data = mstatus;
            12'h301: csr_read_data = misa;
            12'h304: csr_read_data = mie;
            12'h305: csr_read_data = mtvec;
            12'h340: csr_read_data = mscratch;
            12'h341: csr_read_data = mepc;
            12'h342: csr_read_data = mcause;
            12'h344: csr_read_data = mip;
            default: csr_read_data = {XLEN{1'b0}};
        endcase

        if (reset) begin
            csr_ready = 1'b1;
        end 
        else begin
            if (csr_access && !csr_processing) begin
                csr_ready = 1'b0;
            end 
            else if (csr_processing) begin
                csr_ready = 1'b1;
            end 
            else begin
                csr_ready = 1'b1;
            end
        end
    end

    // Reset Operation
    always @(posedge clk or posedge reset) begin
        if (reset) begin
            mtvec   <= DEFAULT_mtvec;
            mscratch <= DEFAULT_mscratch;
            mepc    <= DEFAULT_mepc;
            mcause  <= DEFAULT_mcause;
            mcycle  <= DEFAULT_mcycle;
            minstret <= DEFAULT_minstret;
            mie     <= DEFAULT_mie;

            csr_processing <= 1'b0;
            csr_read_out <= {XLEN{1'b0}};
            
            MIE  <= 1'b0;
            MPIE <= 1'b0;
        end 
        else if (clk_enable) begin
            mcycle <= mcycle + 1;
          
            if (instruction_retired) begin
                minstret <= minstret + 1;
            end
            if (trapped) begin
                MPIE <= MIE;     
                MIE  <= 1'b0;    
            end 
            else if (mret_executed) begin
                MIE  <= MPIE; 
                MPIE <= 1'b1;
            end 
            else if (csr_write_enable && (csr_write_address == 12'h300)) begin
                MIE  <= csr_write_data[3];
                MPIE <= csr_write_data[7];
            end
            if (csr_access && !csr_processing) begin
                csr_processing <= 1'b1;
                csr_read_out <= csr_read_data;
            end 
            else if (csr_processing) begin
                csr_processing <= 1'b0;
                csr_read_out <= csr_read_data;
            end 
            else if (csr_write_enable) begin
                csr_read_out <= csr_read_data;
            end

            // Write Operation
            if (!pre_trap_handler && csr_write_enable) begin
                case (csr_write_address)
                    12'h304: mie    <=   csr_write_data;
                    12'h305: mtvec  <=   csr_write_data;
                    12'h340: mscratch <= csr_write_data;
                    12'h341: mepc   <=   csr_write_data;
                    12'h342: mcause <=   csr_write_data;
                    default: ;
                endcase
            end
            else if (pre_trap_handler) begin
                mepc <= enter_pc;
                mcause <= trap_cause;
            end

        end
    end



endmodule

RTL/RV64/testbenches/CSR_File_tb.v
`timescale 1ns/1ps

module CSRFile_tb;
    reg         clk;
    reg         reset;
    reg         trapped;
    reg         mret_executed;
    reg         csr_write_enable;
    reg  [11:0] csr_read_address;
    reg  [11:0] csr_write_address;
    reg  [31:0] csr_write_data;
    reg instruction_retired;
    reg timer_interrupt_pending;

    // PTH sideband test signals
    reg         pre_trap_handler;
    reg  [31:0] enter_pc;
    reg  [31:0] trap_cause;
    wire [31:0] vector_address;
    wire [31:0] return_address;

    wire [31:0] csr_read_out;
    wire        csr_ready;

    wire        mstatus_mie;
    wire        mie_mtie;

    CSRFile csr_file (
        .clk(clk),
        .clk_enable(1'b1), // Always enabled for testing
        .reset(reset),
        .trapped(trapped),
        .mret_executed(mret_executed),
        .csr_write_enable(csr_write_enable),
        .csr_read_address(csr_read_address),
        .csr_write_address(csr_write_address),
        .csr_write_data(csr_write_data),
        .instruction_retired(instruction_retired),
        .valid_csr_address(1'b1), // Assume all addresses are valid for testing
        .timer_interrupt_pending(timer_interrupt_pending),

        .pre_trap_handler(pre_trap_handler),
        .enter_pc(enter_pc),
        .trap_cause(trap_cause),
        .vector_address(vector_address),
        .return_address(return_address),

        .csr_read_out(csr_read_out),
        .csr_ready(csr_ready), 

        .mstatus_mie(mstatus_mie),
        .mie_mtie(mie_mtie)
    );

    // Generate clock signal, 10ns.
    initial clk = 0;
    always #5 clk = ~clk;

    initial begin
        $dumpfile("./testbenches/results/waveforms/CSR_File.vcd");
        $dumpvars(0, CSRFile_tb);
    end

    initial begin
        $display("==================== CSR File Test START ====================");
        
        // Reset to DEFAULT value, Initialize signals.
        reset = 1;
        trapped = 0;
        mret_executed = 0;
        timer_interrupt_pending = 0;
        csr_write_enable = 0;
        csr_read_address = 12'h000;
        csr_write_address = 12'h000;
        csr_write_data = 32'h0;
        instruction_retired = 0;
        pre_trap_handler = 0;
        enter_pc = 32'h0;
        trap_cause = 32'h0;
        #10;
        reset = 0;
        #10;
        
        // Test 1: Read-only CSRs read.
        csr_read_address = 12'hF11; #10; 
        $display("mvendorid = %h (expected 52564B43)", csr_read_out);
        
        csr_read_address = 12'hF12; #10; 
        instruction_retired = 1'b1; #10;
        instruction_retired = 1'b0;
        $display("marchid = %h (expected 34365335)", csr_read_out);
        
        csr_read_address = 12'hF13; #10;
        $display("mimpid = %h (expected 34364931)", csr_read_out);

        csr_read_address = 12'hF14; #10; 
        $display("mhartid = %h (expected 524B4330)", csr_read_out);

        csr_read_address = 12'h300; #10; 
        $display("mstatus = %h (expected 00001800)", csr_read_out);

        csr_read_address = 12'h301; #10; 
        $display("misa = %h (expected 40000100)", csr_read_out);
        
        // Test 2: MRW CSRs' reset value check
        csr_read_address = 12'h305; #10; 
        $display("mtvec (reset) = %h (expected 00001000)", csr_read_out);
        csr_read_address = 12'h341; #10; 
        $display("mepc  (reset) = %h (expected 00000000)", csr_read_out);
        csr_read_address = 12'h342; #10; 
        $display("mcause(reset) = %h (expected 00000000)", csr_read_out);

        // Test 3: csrrw; mtvec
        csr_read_address = 12'h305; #10; 
        $display("mtvec = %h (expected 00001000)", csr_read_out);

        csr_write_address = 12'h305;
        csr_write_data = 32'h00003000;
        csr_write_enable = 1;
        #10;

        csr_write_enable = 0;
        #10;

        csr_read_address = 12'h305; #10; 
        $display("mtvec = %h (expected 00003000)", csr_read_out);
        
        // Test 4: csrrw; mepc
        csr_read_address = 12'h341; #10;
        $display("mepc = %h (expected 00000000)", csr_read_out);

        csr_write_address = 12'h341;
        csr_write_data = 32'h00004000;
        csr_write_enable = 1;
        #10;

        csr_write_enable = 0;
        #10;

        csr_read_address = 12'h341; #10; 
        $display("mepc = %h (expected 00004000)", csr_read_out);
        
        // Test 5: csrrw; mcause
        csr_read_address = 12'h342; #10; 
        $display("mcause = %h (expected 00000000)", csr_read_out);

        csr_write_address = 12'h342;
        csr_write_data = 32'h00000004;
        csr_write_enable = 1;
        #10;

        csr_write_enable = 0;
        #10;

        csr_read_address = 12'h342;
        #10;

        $display("mcause = %h (expected 00000004)", csr_read_out);
        
        // Test 6: csrrw; Read-only's write ignore test.
        csr_read_address = 12'hF11; #10; 
        $display("Read-only test : mvendorid = %h (expected 52564B43)", csr_read_out);

        csr_write_address = 12'hF11;
        csr_write_data = 32'h00003000;
        csr_write_enable = 1;
        #10;

        csr_write_enable = 0;
        #10;

        csr_read_address = 12'hF11;
        #10;

        $display("Write ignored : mvendorid = %h (expected 52564B43)", csr_read_out);
        
        // Test 7: mcycle/minstret auto-increment check (read-only counters)
        csr_read_address = 12'hB00; #10;
        $display("mcycle (lower 32-bit) = %h (auto-incremented, not 0)", csr_read_out);
        
        csr_read_address = 12'hB80; #10;
        $display("mcycleh (upper 32-bit) = %h (should be 0, no overflow yet)", csr_read_out);
        
        csr_read_address = 12'hB02; #10;
        $display("minstret (lower 32-bit) = %h (should be 1, one instruction retired in Test 1)", csr_read_out);
        
        csr_read_address = 12'hB82; #10;
        $display("minstreth (upper 32-bit) = %h (should be 0, no overflow yet)", csr_read_out);

        // Test 8: Read-only test for mcycle - write should be ignored
        csr_read_address = 12'hB00; #10;
        $display("mcycle (before write attempt) = %h", csr_read_out);

        csr_write_address = 12'hB00;
        csr_write_data = 32'h12345678;
        csr_write_enable = 1;
        #10;

        csr_write_enable = 0;
        #10;

        csr_read_address = 12'hB00; #10;
        $display("mcycle (after write attempt) = %h (write should be ignored, auto-incremented)", csr_read_out);
        
        // Test 9: Read-only test for mcycleh - write should be ignored
        csr_read_address = 12'hB80; #10;
        $display("mcycleh (before write attempt) = %h", csr_read_out);

        csr_write_address = 12'hB80;
        csr_write_data = 32'hABCDEF00;
        csr_write_enable = 1;
        #10;

        csr_write_enable = 0;
        #10;

        csr_read_address = 12'hB80; #10;
        $display("mcycleh (after write attempt) = %h (write should be ignored, should remain 0)", csr_read_out);
        
        // Test 10: Read-only test for minstret - write should be ignored
        csr_read_address = 12'hB02; #10;
        $display("minstret (before write attempt) = %h", csr_read_out);

        csr_write_address = 12'hB02;
        csr_write_data = 32'hDEADBEEF;
        csr_write_enable = 1;
        #10;

        csr_write_enable = 0;
        #10;

        csr_read_address = 12'hB02; #10;
        $display("minstret (after write attempt) = %h (write should be ignored, should remain 1)", csr_read_out);
        
        // Test 11: Read-only test for minstreth - write should be ignored
        csr_read_address = 12'hB82; #10;
        $display("minstreth (before write attempt) = %h", csr_read_out);

        csr_write_address = 12'hB82;
        csr_write_data = 32'hCAFEBABE;
        csr_write_enable = 1;
        #10;

        csr_write_enable = 0;
        #10;

        csr_read_address = 12'hB82; #10;
        $display("minstreth (after write attempt) = %h (write should be ignored, should remain 0)", csr_read_out);
        
        // Test 12: mcycle auto-increment verification
        $display("\n=== Auto-increment verification ===");
        csr_read_address = 12'hB00; 
        #10;
        $display("mcycle at T0 = %h", csr_read_out);
        #20; // Wait 2 cycles
        csr_read_address = 12'hB00; 
        #10;
        $display("mcycle at T0+2 = %h (should be +2 from previous)", csr_read_out);
        
        // Test 13: minstret increment with instruction_retired
        $display("\n=== instruction_retired test ===");
        csr_read_address = 12'hB02;
        #10;
        $display("minstret before retired = %h", csr_read_out);
        
        instruction_retired = 1;
        #10;
        instruction_retired = 0;
        csr_read_address = 12'hB02;
        #10;
        $display("minstret after 1 retired = %h (should be +1)", csr_read_out);
        
        instruction_retired = 1;
        #10;
        instruction_retired = 1;
        #10;
        instruction_retired = 0;
        csr_read_address = 12'hB02;
        #10;
        $display("minstret after 2 more retired = %h (should be +2)", csr_read_out);

        csr_read_address = 12'h344; #10;
        $display("mip = %b (MTIP should be 0)", csr_read_out);
        timer_interrupt_pending = 1;
        #20;
        csr_read_address = 12'h344; #10;
        $display("mip = %b (MTIP should be 1)", csr_read_out);

        // Test 14: Trap & mret Verification
        $display("\n=== Test 14: Trap & mret Verification ===");

        csr_write_address = 12'h300; 
        csr_write_data = 32'h00000008;
        csr_write_enable = 1; #10;
        csr_write_enable = 0; #10;
        
        csr_read_address = 12'h300; #10;
        $display("Before Trap: mstatus = %h (Expected MIE=1, MPIE=0 -> 00001808)", csr_read_out);

        trapped = 1; #10;
        trapped = 0; #10;
        
        csr_read_address = 12'h300; #10;
        $display("After Trap:  mstatus = %h (Expected MIE=0, MPIE=1 -> 00001880)", csr_read_out);

        mret_executed = 1; #10;
        mret_executed = 0; #10;
        
        csr_read_address = 12'h300; #10;
        $display("After mret:  mstatus = %h (Expected MIE=1, MPIE=1 -> 00001888)", csr_read_out);

        //-----------------------
        $display("\n=== Test 15: mscratch R/W Test ===");
        csr_read_address = 12'h340; #10; 
        $display("mscratch (reset) = %h (expected 00000000)", csr_read_out);
        
        csr_write_address = 12'h340;
        csr_write_data = 32'hDEADBEEF; 
        csr_write_enable = 1; #10;
        csr_write_enable = 0; #10;
        
        csr_read_address = 12'h340; #10;
        $display("mscratch (after write) = %h (expected DEADBEEF)", csr_read_out);

        $display("\n=== Test 16: mie (12'h304) and Output Wires Test ===");
        csr_write_address = 12'h304; 
        csr_write_data = 32'h00000080; 
        csr_write_enable = 1; #10;
        csr_write_enable = 0; #10;

        csr_read_address = 12'h304; #10;
        $display("mie = %h (expected 00000080)", csr_read_out);
        $display("mie_mtie wire output = %b (expected 1)", mie_mtie);
        $display("mstatus_mie wire output = %b (current MIE state)", mstatus_mie);

        //---------------



        //-----------------------
        $display("\n=== Test 17: PTH Sideband Path Test ===");

        // 17-1. Set mtvec through the normal CSR write path.
        csr_write_address = 12'h305;
        csr_write_data    = 32'h00007000;
        csr_write_enable  = 1'b1;
        #10;
        csr_write_enable  = 1'b0;
        #10;

        csr_read_address = 12'h305;
        #10;
        $display("PTH mtvec setup: mtvec = %h (expected 00007000)", csr_read_out);

        // 17-2. Enable MIE so trap entry should save MIE into MPIE and clear MIE.
        csr_write_address = 12'h300;
        csr_write_data    = 32'h00000008; // MIE=1, MPIE=0, MPP is hardwired to 11 in DUT
        csr_write_enable  = 1'b1;
        #10;
        csr_write_enable  = 1'b0;
        #10;

        csr_read_address = 12'h300;
        #10;
        $display("Before PTH: mstatus = %h (expected 00001808)", csr_read_out);

        // 17-3. Assert pre_trap_handler and trapped in the same trap-entry cycle.
        // vector_address is combinational, so it should expose mtvec immediately
        // while pre_trap_handler is high, before the next clock edge commits mepc/mcause.
        enter_pc         = 32'h0000028C;
        trap_cause       = 32'h80000007; // Machine timer interrupt
        pre_trap_handler = 1'b1;
        trapped          = 1'b1;
        #1;
        $display("During PTH before posedge: vector_address = %h (expected 00007000)", vector_address);
        $display("During PTH before posedge: return_address = %h (expected 00004000)", return_address);
        #9;
        $display("During PTH after posedge: vector_address = %h (expected 00007000)", vector_address);
        $display("During PTH after posedge: return_address = %h (expected 0000028C)", return_address);

        pre_trap_handler = 1'b0;
        trapped          = 1'b0;
        #1;
        $display("After PTH deassert: vector_address = %h (expected 00000000)", vector_address);
        $display("After PTH deassert: return_address = %h (expected 00000000)", return_address);
        #9;

        // 17-4. Check that PTH sideband wrote mepc/mcause and trap entry updated mstatus.
        csr_read_address = 12'h341;
        #10;
        $display("After PTH: mepc = %h (expected 0000028C)", csr_read_out);

        csr_read_address = 12'h342;
        #10;
        $display("After PTH: mcause = %h (expected 80000007)", csr_read_out);

        csr_read_address = 12'h300;
        #10;
        $display("After PTH: mstatus = %h (expected 00001880)", csr_read_out);

        // 17-5. Normal CSR write must be blocked while pre_trap_handler is active.
        // Try to write mepc through normal CSR path while PTH writes another PC.
        csr_write_address = 12'h341;
        csr_write_data    = 32'hDEADBEEF;
        enter_pc          = 32'h00000ABC;
        trap_cause        = 32'h80000007;
        pre_trap_handler  = 1'b1;
        csr_write_enable  = 1'b1;
        #10;
        pre_trap_handler  = 1'b0;
        csr_write_enable  = 1'b0;
        #10;

        csr_read_address = 12'h341;
        #10;
        $display("PTH priority over CSR write: mepc = %h (expected 00000ABC, not DEADBEEF)", csr_read_out);

        // Final values
        $display("\n=== Final Counter Values ===");
        csr_read_address = 12'hB00; #10;
        $display("Final mcycle[31:0] = %h", csr_read_out);
        
        csr_read_address = 12'hB80; #10;
        $display("Final mcycle[63:32] = %h", csr_read_out);
        $display("Final Full mcycle = 0x%h_%h", csr_file.mcycle[63:32], csr_file.mcycle[31:0]);
        
        csr_read_address = 12'hB02; #10;
        $display("Final minstret[31:0] = %h", csr_read_out);
        
        csr_read_address = 12'hB82; #10;
        $display("Final minstret[63:32] = %h", csr_read_out);
        $display("Final Full minstret = 0x%h_%h", csr_file.minstret[63:32], csr_file.minstret[31:0]);
        
        $display("\n====================  CSR File Test END  ====================");

        $stop;
    end
    
endmodule

RTL/RV64/testbenches/results/waveforms/CSR_File.vcd
$date
	Fri May  8 16:02:37 2026
$end
$version
	Icarus Verilog
$end
$timescale
	1ps
$end
$scope module CSRFile_tb $end
$var wire 32 ! vector_address [31:0] $end
$var wire 32 " return_address [31:0] $end
$var wire 1 # mstatus_mie $end
$var wire 1 $ mie_mtie $end
$var wire 1 % csr_ready $end
$var wire 32 & csr_read_out [31:0] $end
$var reg 1 ' clk $end
$var reg 12 ( csr_read_address [11:0] $end
$var reg 12 ) csr_write_address [11:0] $end
$var reg 32 * csr_write_data [31:0] $end
$var reg 1 + csr_write_enable $end
$var reg 32 , enter_pc [31:0] $end
$var reg 1 - instruction_retired $end
$var reg 1 . mret_executed $end
$var reg 1 / pre_trap_handler $end
$var reg 1 0 reset $end
$var reg 1 1 timer_interrupt_pending $end
$var reg 32 2 trap_cause [31:0] $end
$var reg 1 3 trapped $end
$scope module csr_file $end
$var wire 2 4 MPP [1:0] $end
$var wire 1 ' clk $end
$var wire 1 5 clk_enable $end
$var wire 1 6 csr_access $end
$var wire 12 7 csr_read_address [11:0] $end
$var wire 12 8 csr_write_address [11:0] $end
$var wire 32 9 csr_write_data [31:0] $end
$var wire 1 + csr_write_enable $end
$var wire 32 : enter_pc [31:0] $end
$var wire 1 - instruction_retired $end
$var wire 32 ; marchid [31:0] $end
$var wire 32 < mhartid [31:0] $end
$var wire 32 = mimpid [31:0] $end
$var wire 32 > misa [31:0] $end
$var wire 1 . mret_executed $end
$var wire 1 # mstatus_mie $end
$var wire 32 ? mvendorid [31:0] $end
$var wire 1 / pre_trap_handler $end
$var wire 1 0 reset $end
$var wire 1 1 timer_interrupt_pending $end
$var wire 32 @ trap_cause [31:0] $end
$var wire 1 3 trapped $end
$var wire 1 A valid_csr_address $end
$var wire 32 B vector_address [31:0] $end
$var wire 32 C return_address [31:0] $end
$var wire 32 D mstatus [31:0] $end
$var wire 32 E mip [31:0] $end
$var wire 1 $ mie_mtie $end
$var parameter 32 F DEFAULT_mcause $end
$var parameter 32 G DEFAULT_mcycle $end
$var parameter 32 H DEFAULT_mepc $end
$var parameter 32 I DEFAULT_mie $end
$var parameter 32 J DEFAULT_minstret $end
$var parameter 32 K DEFAULT_mscratch $end
$var parameter 32 L DEFAULT_mtvec $end
$var parameter 32 M XLEN $end
$var reg 1 N MIE $end
$var reg 1 O MPIE $end
$var reg 1 P csr_processing $end
$var reg 32 Q csr_read_data [31:0] $end
$var reg 32 R csr_read_out [31:0] $end
$var reg 1 % csr_ready $end
$var reg 32 S mcause [31:0] $end
$var reg 64 T mcycle [63:0] $end
$var reg 32 U mepc [31:0] $end
$var reg 32 V mie [31:0] $end
$var reg 64 W minstret [63:0] $end
$var reg 32 X mscratch [31:0] $end
$var reg 32 Y mtvec [31:0] $end
$upscope $end
$upscope $end
$enddefinitions $end
$comment Show the parameter values. $end
$dumpall
b100000 M
b110110101100000 L
b0 K
b0 J
b0 I
b0 H
b0 G
b0 F
$end
#0
$dumpvars
b110110101100000 Y
b0 X
b0 W
b0 V
b0 U
b0 T
b0 S
b0 R
b0 Q
0P
0O
0N
b0 E
b1100000000000 D
b0 C
b0 B
1A
b0 @
b1010010010101100100101101000011 ?
b1000000000000000001000100000000 >
b110100001101100100100100110001 =
b0 <
b110100001101100101001100110101 ;
b0 :
b0 9
b0 8
b0 7
16
15
b11 4
03
b0 2
01
10
0/
0.
0-
b0 ,
0+
b0 *
b0 )
b0 (
0'
b0 &
1%
0$
0#
b0 "
b0 !
$end
#5000
1'
#10000
0%
0'
00
#15000
1%
1P
b1 T
1'
#20000
b1010010010101100100101101000011 Q
0'
b111100010001 (
b111100010001 7
#25000
0%
b1010010010101100100101101000011 &
b1010010010101100100101101000011 R
0P
b10 T
1'
#30000
b110100001101100101001100110101 Q
0'
b111100010010 (
b111100010010 7
#35000
1%
b110100001101100101001100110101 &
b110100001101100101001100110101 R
1P
b11 T
1'
#40000
0'
1-
#45000
0%
0P
b1 W
b100 T
1'
#50000
b110100001101100100100100110001 Q
0'
b111100010011 (
b111100010011 7
0-
#55000
1%
b110100001101100100100100110001 &
b110100001101100100100100110001 R
1P
b101 T
1'
#60000
b0 Q
0'
b111100010100 (
b111100010100 7
#65000
0%
b0 &
b0 R
0P
b110 T
1'
#70000
b1100000000000 Q
0'
b1100000000 (
b1100000000 7
#75000
1%
b1100000000000 &
b1100000000000 R
1P
b111 T
1'
#80000
b1000000000000000001000100000000 Q
0'
b1100000001 (
b1100000001 7
#85000
0%
b1000000000000000001000100000000 &
b1000000000000000001000100000000 R
0P
b1000 T
1'
#90000
b110110101100000 Q
0'
b1100000101 (
b1100000101 7
#95000
1%
b110110101100000 &
b110110101100000 R
1P
b1001 T
1'
#100000
b0 Q
0'
b1101000001 (
b1101000001 7
#105000
0%
b0 &
b0 R
0P
b1010 T
1'
#110000
0'
b1101000010 (
b1101000010 7
#115000
1%
1P
b1011 T
1'
#120000
b110110101100000 Q
0'
b1100000101 (
b1100000101 7
#125000
0%
b110110101100000 &
b110110101100000 R
0P
b1100 T
1'
#130000
0'
1+
b11000000000000 *
b11000000000000 9
b1100000101 )
b1100000101 8
#135000
1%
b11000000000000 Q
b11000000000000 Y
1P
b1101 T
1'
#140000
0'
0+
#145000
0%
b11000000000000 &
b11000000000000 R
0P
b1110 T
1'
#150000
0'
#155000
1%
1P
b1111 T
1'
#160000
b0 Q
0'
b1101000001 (
b1101000001 7
#165000
0%
b0 &
b0 R
0P
b10000 T
1'
#170000
0'
1+
b100000000000000 *
b100000000000000 9
b1101000001 )
b1101000001 8
#175000
1%
b100000000000000 Q
b100000000000000 U
1P
b10001 T
1'
#180000
0'
0+
#185000
0%
b100000000000000 &
b100000000000000 R
0P
b10010 T
1'
#190000
0'
#195000
1%
1P
b10011 T
1'
#200000
b0 Q
0'
b1101000010 (
b1101000010 7
#205000
0%
b0 &
b0 R
0P
b10100 T
1'
#210000
0'
1+
b100 *
b100 9
b1101000010 )
b1101000010 8
#215000
1%
b100 Q
b100 S
1P
b10101 T
1'
#220000
0'
0+
#225000
0%
b100 &
b100 R
0P
b10110 T
1'
#230000
0'
#235000
1%
1P
b10111 T
1'
#240000
b1010010010101100100101101000011 Q
0'
b111100010001 (
b111100010001 7
#245000
0%
b1010010010101100100101101000011 &
b1010010010101100100101101000011 R
0P
b11000 T
1'
#250000
0'
1+
b11000000000000 *
b11000000000000 9
b111100010001 )
b111100010001 8
#255000
1%
1P
b11001 T
1'
#260000
0'
0+
#265000
0%
0P
b11010 T
1'
#270000
0'
#275000
1%
1P
b11011 T
1'
#280000
b11011 Q
0'
b101100000000 (
b101100000000 7
#285000
0%
b11100 Q
b11011 &
b11011 R
0P
b11100 T
1'
#290000
b0 Q
0'
b101110000000 (
b101110000000 7
#295000
1%
b0 &
b0 R
1P
b11101 T
1'
#300000
b1 Q
0'
b101100000010 (
b101100000010 7
#305000
0%
b1 &
b1 R
0P
b11110 T
1'
#310000
b0 Q
0'
b101110000010 (
b101110000010 7
#315000
1%
b0 &
b0 R
1P
b11111 T
1'
#320000
b11111 Q
0'
b101100000000 (
b101100000000 7
#325000
0%
b100000 Q
b11111 &
b11111 R
0P
b100000 T
1'
#330000
0'
1+
b10010001101000101011001111000 *
b10010001101000101011001111000 9
b101100000000 )
b101100000000 8
#335000
1%
b100001 Q
b100000 &
b100000 R
1P
b100001 T
1'
#340000
0'
0+
#345000
0%
b100010 Q
b100001 &
b100001 R
0P
b100010 T
1'
#350000
0'
#355000
1%
b100011 Q
b100010 &
b100010 R
1P
b100011 T
1'
#360000
b0 Q
0'
b101110000000 (
b101110000000 7
#365000
0%
b0 &
b0 R
0P
b100100 T
1'
#370000
0'
1+
b10101011110011011110111100000000 *
b10101011110011011110111100000000 9
b101110000000 )
b101110000000 8
#375000
1%
1P
b100101 T
1'
#380000
0'
0+
#385000
0%
0P
b100110 T
1'
#390000
0'
#395000
1%
1P
b100111 T
1'
#400000
b1 Q
0'
b101100000010 (
b101100000010 7
#405000
0%
b1 &
b1 R
0P
b101000 T
1'
#410000
0'
1+
b11011110101011011011111011101111 *
b11011110101011011011111011101111 9
b101100000010 )
b101100000010 8
#415000
1%
1P
b101001 T
1'
#420000
0'
0+
#425000
0%
0P
b101010 T
1'
#430000
0'
#435000
1%
1P
b101011 T
1'
#440000
b0 Q
0'
b101110000010 (
b101110000010 7
#445000
0%
b0 &
b0 R
0P
b101100 T
1'
#450000
0'
1+
b11001010111111101011101010111110 *
b11001010111111101011101010111110 9
b101110000010 )
b101110000010 8
#455000
1%
1P
b101101 T
1'
#460000
0'
0+
#465000
0%
0P
b101110 T
1'
#470000
0'
#475000
1%
1P
b101111 T
1'
#480000
b101111 Q
0'
b101100000000 (
b101100000000 7
#485000
0%
b110000 Q
b101111 &
b101111 R
0P
b110000 T
1'
#490000
0'
#495000
1%
b110001 Q
b110000 &
b110000 R
1P
b110001 T
1'
#500000
0'
#505000
0%
b110010 Q
b110001 &
b110001 R
0P
b110010 T
1'
#510000
0'
#515000
1%
b110011 Q
b110010 &
b110010 R
1P
b110011 T
1'
#520000
b1 Q
0'
b101100000010 (
b101100000010 7
#525000
0%
b1 &
b1 R
0P
b110100 T
1'
#530000
0'
1-
#535000
1%
b10 Q
1P
b10 W
b110101 T
1'
#540000
0'
0-
#545000
0%
b10 &
b10 R
0P
b110110 T
1'
#550000
0'
1-
#555000
1%
b11 Q
1P
b11 W
b110111 T
1'
#560000
0'
#565000
0%
b100 Q
b11 &
b11 R
0P
b100 W
b111000 T
1'
#570000
0'
0-
#575000
1%
b100 &
b100 R
1P
b111001 T
1'
#580000
b0 Q
0'
b1101000100 (
b1101000100 7
#585000
0%
b0 &
b0 R
0P
b111010 T
1'
#590000
b10000000 Q
0'
b10000000 E
11
#595000
1%
b10000000 &
b10000000 R
1P
b111011 T
1'
#600000
0'
#605000
0%
0P
b111100 T
1'
#610000
0'
#615000
1%
1P
b111101 T
1'
#620000
0'
1+
b1000 *
b1000 9
b1100000000 )
b1100000000 8
#625000
0%
0P
b1100000001000 D
1#
1N
b111110 T
1'
#630000
0'
0+
#635000
1%
1P
b111111 T
1'
#640000
b1100000001000 Q
0'
b1100000000 (
b1100000000 7
#645000
0%
b1100000001000 &
b1100000001000 R
0P
b1000000 T
1'
#650000
0'
13
#655000
1%
b1100010000000 Q
1P
0#
0N
b1100010000000 D
1O
b1000001 T
1'
#660000
0'
03
#665000
0%
b1100010000000 &
b1100010000000 R
0P
b1000010 T
1'
#670000
0'
#675000
1%
1P
b1000011 T
1'
#680000
0'
1.
#685000
0%
b1100010001000 Q
0P
b1100010001000 D
1#
1N
b1000100 T
1'
#690000
0'
0.
#695000
1%
b1100010001000 &
b1100010001000 R
1P
b1000101 T
1'
#700000
0'
#705000
0%
0P
b1000110 T
1'
#710000
b0 Q
0'
b1101000000 (
b1101000000 7
#715000
1%
b0 &
b0 R
1P
b1000111 T
1'
#720000
0'
1+
b11011110101011011011111011101111 *
b11011110101011011011111011101111 9
b1101000000 )
b1101000000 8
#725000
0%
b11011110101011011011111011101111 Q
b11011110101011011011111011101111 X
0P
b1001000 T
1'
#730000
0'
0+
#735000
1%
b11011110101011011011111011101111 &
b11011110101011011011111011101111 R
1P
b1001001 T
1'
#740000
0'
#745000
0%
0P
b1001010 T
1'
#750000
0'
1+
b10000000 *
b10000000 9
b1100000100 )
b1100000100 8
#755000
1$
1%
b10000000 V
1P
b1001011 T
1'
#760000
0'
0+
#765000
0%
0P
b1001100 T
1'
#770000
b10000000 Q
0'
b1100000100 (
b1100000100 7
#775000
1%
b10000000 &
b10000000 R
1P
b1001101 T
1'
#780000
0'
1+
b111000000000000 *
b111000000000000 9
b1100000101 )
b1100000101 8
